dia/__init__.py
dia/cli.py
dia/data_types.py
dia/utils.py
dia-0.1.8.dist-info/entry_points.txt
dia-0.1.8.dist-info/LICENSE
dia-0.1.8.dist-info/WHEEL
dia-0.1.8.dist-info/METADATA
dia-0.1.8.dist-info/RECORD
